README.md
dove.py
setup.py
dove_docker.egg-info/PKG-INFO
dove_docker.egg-info/SOURCES.txt
dove_docker.egg-info/dependency_links.txt
dove_docker.egg-info/entry_points.txt
dove_docker.egg-info/requires.txt
dove_docker.egg-info/top_level.txt