Metadata-Version: 2.1
Name: dove-docker
Version: 0.0.6
Summary: A tool to extend the docker functionality to include an incremental tag versioning system for docker images
Home-page: https://github.com/intech-iiot/dove
Author: Usman Shahid
Author-email: u.manshahid@gmail.com
License: Apache 2.0
Platform: UNKNOWN
